Metadata-Version: 2.1
Name: pmemkv
Version: 1.0
Summary: Python bindings for PMEMKV library
Home-page: https://pmem.io/pmemkv-python
Author: Pmemkv development team
License: UNKNOWN
Project-URL: Source Code, https://github.com/pmem/pmemkv-python
Project-URL: Bug Reports, https://github.com/pmem/pmemkv-python/issues
Project-URL: Pmemkv, https://github.com/pmem/pmemkv
Platform: UNKNOWN
Classifier: Development Status :: 5 - Production/Stable
Classifier: Intended Audience :: Developers
Classifier: License :: OSI Approved :: BSD License
Classifier: Operating System :: POSIX :: Linux
Classifier: Programming Language :: Python :: 3
Classifier: Topic :: Software Development :: Libraries
Requires-Python: >=3.6
